urban_env/__init__.py
urban_env/interval.py
urban_env/logger.py
urban_env/setup.py
urban_env/utils.py
urban_env/envs/LG_sim_env.py
urban_env/envs/__init__.py
urban_env/envs/abstract.py
urban_env/envs/finite_mdp.py
urban_env/envs/graphics.py
urban_env/envs/merge_env.py
urban_env/envs/multilane_env.py
urban_env/envs/observation.py
urban_env/envs/parking_env.py
urban_env/envs/parking_env_2outs.py
urban_env/envs/roundabout_env.py
urban_env/envs/test_success_threshold.py
urban_env/envs/two_way_env.py
urban_env/envs/lgsvl/__init__.py
urban_env/envs/lgsvl/agent.py
urban_env/envs/lgsvl/geometry.py
urban_env/envs/lgsvl/remote.py
urban_env/envs/lgsvl/sensor.py
urban_env/envs/lgsvl/simulator.py
urban_env/envs/lgsvl/utils.py
urban_env/road/__init__.py
urban_env/road/graphics.py
urban_env/road/lane.py
urban_env/road/road.py
urban_env/vehicle/__init__.py
urban_env/vehicle/behavior.py
urban_env/vehicle/control.py
urban_env/vehicle/dynamics.py
urban_env/vehicle/graphics.py
urban_env/vehicle/uncertainty.py
urban_env-0.0.dev2.dist-info/METADATA
urban_env-0.0.dev2.dist-info/RECORD
urban_env-0.0.dev2.dist-info/WHEEL
urban_env-0.0.dev2.dist-info/entry_points.txt
urban_env-0.0.dev2.dist-info/top_level.txt
